geowheel/__init__.py
geowheel/ellipsoid.cp312-win_amd64.pyd
ellipsoid-2025.2.7.dist-info/METADATA
ellipsoid-2025.2.7.dist-info/WHEEL
ellipsoid-2025.2.7.dist-info/top_level.txt
ellipsoid-2025.2.7.dist-info/RECORD
