Metadata-Version: 2.2
Name: ellipsoid
Version: 2025.2.7
Summary: 参考椭球体基础软件包，主要包括：Geometry-几何要素类；Topology-几何要素拓扑类；MapGrid-国际标准比例尺图幅分幅网格类；Projection-几何要素坐标投影变换类；ProjectionHelper-几何要素坐标投影助手类；Astronomy-天文寻星计算类
Author: GeoWheel Studio
Author-email: flylyisflying@gmail.com
License: MIT
Keywords: geometry,geojson,gml,kml,topology,projection,mapgrid,astronomy
Requires-Python: >=3.9
Requires-Dist: pygml
Requires-Dist: shapely
Requires-Dist: lxml
Requires-Dist: gdal
Requires-Dist: pytz
Dynamic: author
Dynamic: author-email
Dynamic: description
Dynamic: description-content-type
Dynamic: keywords
Dynamic: license
Dynamic: requires-dist
Dynamic: requires-python
Dynamic: summary
